configset/__init__.py
configset/__version__.py
configset/configset.py
configset/test.py
configset-1.86.dist-info/METADATA
configset-1.86.dist-info/WHEEL
configset-1.86.dist-info/entry_points.txt
configset-1.86.dist-info/top_level.txt
configset-1.86.dist-info/RECORD
