Metadata-Version: 2.4
Name: configset
Version: 1.86
Summary: A powerful and flexible configuration management library that supports both INI and JSON formats with automatic type conversion, list/dictionary parsing, and class-based interfaces.
Home-page: https://github.com/cumulus13/configset
Author: Hadi Cahyadi
Author-email: cumulus13@gmail.com
Maintainer: cumulus13
Maintainer-email: cumulus13@gmail.com
License: MIT
Project-URL: Documentation, https://github.com/cumulus13/configset/wiki
Project-URL: Source Code, https://github.com/cumulus13/configset
Project-URL: Bug Tracker, https://github.com/cumulus13/configset/issues
Project-URL: Changelog, https://github.com/cumulus13/configset/releases
Keywords: configuration,config,ini,json,settings,configparser,management,file,parser,setup
Platform: any
Classifier: Development Status :: 5 - Production/Stable
Classifier: Intended Audience :: Developers
Classifier: Intended Audience :: System Administrators
Classifier: License :: OSI Approved :: MIT License
Classifier: Operating System :: OS Independent
Classifier: Programming Language :: Python
Classifier: Programming Language :: Python :: 2
Classifier: Programming Language :: Python :: 2.7
Classifier: Programming Language :: Python :: 3
Classifier: Programming Language :: Python :: 3.6
Classifier: Programming Language :: Python :: 3.7
Classifier: Programming Language :: Python :: 3.8
Classifier: Programming Language :: Python :: 3.9
Classifier: Programming Language :: Python :: 3.10
Classifier: Programming Language :: Python :: 3.11
Classifier: Programming Language :: Python :: 3.12
Classifier: Topic :: Software Development :: Libraries :: Python Modules
Classifier: Topic :: System :: Systems Administration
Classifier: Topic :: Utilities
Classifier: Topic :: Software Development :: Libraries
Classifier: Topic :: Text Processing :: General
Requires-Python: >=2.7, !=3.0.*, !=3.1.*, !=3.2.*, !=3.3.*, !=3.4.*, !=3.5.*
Requires-Dist: rich>=10.0.0
Requires-Dist: pyyaml
Provides-Extra: full
Requires-Dist: rich>=10.0.0; extra == "full"
Requires-Dist: make-colors>=1.0.0; extra == "full"
Requires-Dist: json; extra == "full"
Requires-Dist: pyyaml; extra == "full"
Requires-Dist: licface; extra == "full"
Requires-Dist: jsoncolor>=0.2.0; extra == "full"
Requires-Dist: richcolorlog; extra == "full"
Provides-Extra: colors
Requires-Dist: rich>=10.0.0; extra == "colors"
Requires-Dist: make-colors>=1.0.0; extra == "colors"
Requires-Dist: licface; extra == "colors"
Requires-Dist: jsoncolor>=0.2.0; extra == "colors"
Requires-Dist: richcolorlog; extra == "colors"
Provides-Extra: json
Requires-Dist: jsoncolor>=0.2.0; extra == "json"
Provides-Extra: dev
Requires-Dist: pytest>=4.0.0; extra == "dev"
Requires-Dist: pytest-cov>=2.8.0; extra == "dev"
Requires-Dist: black>=19.0.0; extra == "dev"
Requires-Dist: isort>=4.3.0; extra == "dev"
Requires-Dist: mypy>=0.700; extra == "dev"
Requires-Dist: flake8>=3.7.0; extra == "dev"
Dynamic: author
Dynamic: author-email
Dynamic: classifier
Dynamic: description
Dynamic: description-content-type
Dynamic: home-page
Dynamic: keywords
Dynamic: license
Dynamic: maintainer
Dynamic: maintainer-email
Dynamic: platform
Dynamic: project-url
Dynamic: provides-extra
Dynamic: requires-dist
Dynamic: requires-python
Dynamic: summary
